{
	"models": [
		{"id": "skybox", "VD": "VDskybox", "model": "assets/models/SkyBoxCube.obj", "format":"OBJ"},
		{"id": "ap", "VD": "VDsimp", "model": "assets/models/aeroplanino.obj", "format": "OBJ"},
		{"id": "ap_rotor", "VD": "VDsimp", "model": "assets/models/aeroplanino_motore.obj", "format": "OBJ"},
		{"id": "2Dplane", "VD": "VDsimp", "model": "assets/models/plane.obj", "format": "OBJ"},
		{"id": "2DplaneTan", "VD": "VDtan", "model": "assets/models/2Dplane_high_res.gltf", "format": "GLTF"},
		{"id": "gem", "VD": "VDsimp", "model": "assets/models/Gem01_Blue.mgcg", "format": "MGCG"},
		{"id": "Tree", "VD": "VDsimp", "model":  "assets/models/vegetation.030.mgcg", "format":  "MGCG"}
	],
	"textures": [
		{"id": "pnois", "texture": "assets/textures/Perlin_noise.png", "format": "D"},
		{"id": "skybox", "texture": "assets/textures/daybox_2.hdr", "format": "C"},
		{"id": "ap", "texture": "assets/textures/airplane.jpg", "format": "C"},

		{"id": "gem", "texture": "assets/textures/Gem01_Blue_Albedo.png", "format": "C"},
		{"id": "gemMetallic", "texture": "assets/textures/Gem01_Blue_MetallicSmoothness.png", "format": "D"},

		{"id": "GrassAlbedo", "texture": "assets/textures/GrassTexture/grass_albedo.jpg", "format": "C"},
		{"id": "GrassNm", "texture": "assets/textures/GrassTexture/grass_nm.jpg", "format": "D"},
		{"id": "GrassOcclusion", "texture": "assets/textures/GrassTexture/grass_occlusion.jpg", "format": "D"},
		{"id": "GrassRoughness", "texture": "assets/textures/GrassTexture/grass_roughness.jpg", "format": "D"},
		{"id": "Tree", "texture": "assets/textures/Textures_Vegetation.png", "format": "C"},
		{"id": "water", "texture": "assets/textures/water_albedo.jpg", "format": "C"}


	],
	"instances": [
		{"technique": "CookTorranceNoiseSimp", "elements": [
			{"id": "ap",  "model": "ap",   "texture": ["ap", "pnois"],
				"eulerAngles": [0, 180, 0],
				"scale": [0.25, 0.25, 0.25],
				"translate": [-10, 0.5, 0]
			},
			{"id": "ap_rotor",  "model": "ap_rotor",   "texture": ["ap", "pnois"],
				"eulerAngles": [0, 0, 0],
				"scale": [0.25, 0.25, 0.25],
				"translate": [-10, 0.5, 0]
			},
			{"id": "Tree1",  "model": "Tree",   "texture": ["Tree", "pnois"],
				"scale": [4, 4, 4]
			},
			{"id": "Tree2",  "model": "Tree",   "texture": ["Tree", "pnois"],
				"scale": [4, 4, 4]
			},
			{"id": "Tree3",  "model": "Tree",   "texture": ["Tree", "pnois"],
				"scale": [4, 4, 4]
			},
			{"id": "Tree4",  "model": "Tree",   "texture": ["Tree", "pnois"],
				"scale": [4, 4, 4]
			},
			{"id": "Tree5",  "model": "Tree",   "texture": ["Tree", "pnois"],
				"scale": [4, 4, 4]
			},
			{"id": "Tree6",  "model": "Tree",   "texture": ["Tree", "pnois"],
				"scale": [4, 4, 4]
			},
			{"id": "Tree7",  "model": "Tree",   "texture": ["Tree", "pnois"],
				"scale": [4, 4, 4]
			},
			{"id": "Tree8",  "model": "Tree",   "texture": ["Tree", "pnois"],
				"scale": [4, 4, 4]
			},
			{"id": "Tree9",  "model": "Tree",   "texture": ["Tree", "pnois"],
				"scale": [4, 4, 4]
			},
			{"id": "Tree10",  "model": "Tree",   "texture": ["Tree", "pnois"],
				"scale": [4, 4, 4]
			},
			{"id": "Tree11",  "model": "Tree",   "texture": ["Tree", "pnois"],
				"scale": [4, 4, 4]
			},
			{"id": "Tree12",  "model": "Tree",   "texture": ["Tree", "pnois"],
				"scale": [4, 4, 4]
			},
			{"id": "Tree13",  "model": "Tree",   "texture": ["Tree", "pnois"],
				"scale": [4, 4, 4]
			},
			{"id": "Tree14",  "model": "Tree",   "texture": ["Tree", "pnois"],
				"scale": [4, 4, 4]
			},
			{"id": "Tree15",  "model": "Tree",   "texture": ["Tree", "pnois"],
				"scale": [4, 4, 4]
			},
			{"id": "Tree16",  "model": "Tree",   "texture": ["Tree", "pnois"],
				"scale": [4, 4, 4]
			},
			{"id": "Tree17",  "model": "Tree",   "texture": ["Tree", "pnois"],
				"scale": [4, 4, 4]
			},
			{"id": "Tree18",  "model": "Tree",   "texture": ["Tree", "pnois"],
				"scale": [4, 4, 4]
			},
			{"id": "Tree19",  "model": "Tree",   "texture": ["Tree", "pnois"],
				"scale": [4, 4, 4]
			},
			{"id": "Tree20",  "model": "Tree",   "texture": ["Tree", "pnois"],
				"scale": [4, 4, 4]
			},
			{"id": "Tree21",  "model": "Tree",   "texture": ["Tree", "pnois"],
				"scale": [4, 4, 4]
			},
			{"id": "Tree22",  "model": "Tree",   "texture": ["Tree", "pnois"],
				"scale": [4, 4, 4]
			},
			{"id": "Tree23",  "model": "Tree",   "texture": ["Tree", "pnois"],
				"scale": [4, 4, 4]
			},
			{"id": "Tree24",  "model": "Tree",   "texture": ["Tree", "pnois"],
				"scale": [4, 4, 4]
			},
			{"id": "Tree25",  "model": "Tree",   "texture": ["Tree", "pnois"],
				"scale": [4, 4, 4]
			},
			{"id": "Tree26",  "model": "Tree",   "texture": ["Tree", "pnois"],
				"scale": [4, 4, 4]
			},
			{"id": "Tree27",  "model": "Tree",   "texture": ["Tree", "pnois"],
				"scale": [4, 4, 4]
			},
			{"id": "Tree28",  "model": "Tree",   "texture": ["Tree", "pnois"],
				"scale": [4, 4, 4]
			},
			{"id": "Tree29",  "model": "Tree",   "texture": ["Tree", "pnois"],
				"scale": [4, 4, 4]
			},
			{"id": "Tree30",  "model": "Tree",   "texture": ["Tree", "pnois"],
				"scale": [4, 4, 4]
			}

		]},
		{"technique": "CookTorranceGem", "elements": [
			{"id": "gem1",  "model": "gem",   "texture": ["gem", "gemMetallic"],
				"scale": [5, 5, 5],
				"translate": [0, 0, 0],
				"eulerAngles": [90, 0, 0]
			},
			{"id": "gem2",  "model": "gem",   "texture": ["gem", "gemMetallic"],
				"scale": [5, 5, 5],
				"translate": [0, 0, 0],
				"eulerAngles": [90, 0, 0]
			},
			{"id": "gem3",  "model": "gem",   "texture": ["gem", "gemMetallic"],
				"scale": [5, 5, 5],
				"translate": [0, 0, 0],
				"eulerAngles": [90, 0, 0]
			},
			{"id": "gem4",  "model": "gem",   "texture": ["gem", "gemMetallic"],
				"scale": [5, 5, 5],
				"translate": [0, 0, 0],
				"eulerAngles": [90, 0, 0]
			},
			{"id": "gem5",  "model": "gem",   "texture": ["gem", "gemMetallic"],
				"scale": [5, 5, 5],
				"translate": [0, 0, 0],
				"eulerAngles": [90, 0, 0]
			},
			{"id": "gem6",  "model": "gem",   "texture": ["gem", "gemMetallic"],
				"scale": [5, 5, 5],
				"translate": [0, 0, 0],
				"eulerAngles": [90, 0, 0]
			},
			{"id": "gem7",  "model": "gem",   "texture": ["gem", "gemMetallic"],
				"scale": [5, 5, 5],
				"translate": [0, 0, 0],
				"eulerAngles": [90, 0, 0]
			},
			{"id": "gem8",  "model": "gem",   "texture": ["gem", "gemMetallic"],
				"scale": [5, 5, 5],
				"translate": [0, 0, 0],
				"eulerAngles": [90, 0, 0]
			},
			{"id": "gem9",  "model": "gem",   "texture": ["gem", "gemMetallic"],
				"scale": [5, 5, 5],
				"translate": [0, 0, 0],
				"eulerAngles": [90, 0, 0]
			},
			{"id": "gem10",  "model": "gem",   "texture": ["gem", "gemMetallic"],
				"scale": [5, 5, 5],
				"translate": [0, 0, 0],
				"eulerAngles": [90, 0, 0]
			}
		]},
		{"technique": "SkyBox", "elements": [
			{"id": "skybox",  "model": "skybox",   "texture": ["skybox"]}
		]},
		{"technique": "PBR", "elements": [
			{"id": "2DplaneTan",  "model": "2DplaneTan",   "texture": ["GrassAlbedo", "GrassNm", "GrassOcclusion", "GrassRoughness", "water"],
				"scale": [500, 500, 500]
			}
		]}
	]
}